guidewd_sitemap_generator/__init__.py
guidewd_sitemap_generator/cli_sitemap_generator.py
guidewd_sitemap_generator-0.1.1.dist-info/LICENSE.txt
guidewd_sitemap_generator-0.1.1.dist-info/METADATA
guidewd_sitemap_generator-0.1.1.dist-info/WHEEL
guidewd_sitemap_generator-0.1.1.dist-info/entry_points.txt
guidewd_sitemap_generator-0.1.1.dist-info/top_level.txt
guidewd_sitemap_generator-0.1.1.dist-info/RECORD
