Metadata-Version: 2.1
Name: guidewd-sitemap-generator
Version: 0.1.1
Summary: A command-line tool to generate sitemaps for a given URL.
Home-page: https://github.com/KartikeyDhaka/GuideWD
Author: Raghava Lab
Author-email: raghava@iiitd.ac.in
Classifier: Programming Language :: Python :: 3
Classifier: License :: OSI Approved :: MIT License
Classifier: Operating System :: OS Independent
Requires-Python: >=3.6
License-File: LICENSE.txt
